molddir/__init__.py
molddir/decoder.py
molddir/encoder.py
molddir/keys.py
molddir/main.py
molddir/utility.py
molddir/walker.py
molddir-0.1.5.dist-info/LICENSE
molddir-0.1.5.dist-info/METADATA
molddir-0.1.5.dist-info/WHEEL
molddir-0.1.5.dist-info/entry_points.txt
molddir-0.1.5.dist-info/RECORD
