Metadata-Version: 2.1
Name: molddir
Version: 0.1.5
Summary: molddir simplifies merging directory files into a single file. It's especially useful for sending entire codebases to Large Language Models (LLMs) by encoding the codebase into one string
Home-page: https://github.com/RahulDas-dev/molddir/
License: MIT
Keywords: llm for coding,code Compression,Directory Falttening
Author: RahulDas-dev
Author-email: r.das699@gmail.com
Maintainer: RahulDas-dev
Maintainer-email: r.das699@gmail.com
Requires-Python: >=3.9,<4.0
Classifier: License :: OSI Approved :: MIT License
Classifier: Programming Language :: Python :: 3
Classifier: Programming Language :: Python :: 3.9
Classifier: Programming Language :: Python :: 3.10
Classifier: Programming Language :: Python :: 3.11
Classifier: Programming Language :: Python :: 3.12
Project-URL: Documentation, https://github.com/RahulDas-dev/molddir/
Project-URL: Repository, https://github.com/RahulDas-dev/molddir/
